text_toolkit/__init__.py
text_toolkit/analyze.py
TextToolkit-0.0.3.dist-info/LICENSE.txt
TextToolkit-0.0.3.dist-info/METADATA
TextToolkit-0.0.3.dist-info/WHEEL
TextToolkit-0.0.3.dist-info/top_level.txt
TextToolkit-0.0.3.dist-info/RECORD
