Metadata-Version: 2.1
Name: TextToolkit
Version: 0.0.3
Summary: Toolkit for mining unstructured text information
Home-page: https://github.com/wesleyLaurence/TextToolkit
Author: Wesley Laurence
Author-email: wesleylaurencetech@gmail.com
License: UNKNOWN
Platform: UNKNOWN
Classifier: Programming Language :: Python :: 3
Classifier: License :: OSI Approved :: MIT License
Classifier: Operating System :: OS Independent
Requires-Python: >=3.6
Requires-Dist: pandas
Requires-Dist: matplotlib
Requires-Dist: seaborn
